{"0":{"id":"61898245d21f9","name":"tomas","email":"tomas.com","phoneNumber":"32132132","nin":"32132132132","date":"2022.12.12","time":"11:00"},"1":{"id":"618a8acb6c963","name":"romas","email":"romas.com","phoneNumber":"23423423","nin":"23423423423","date":"2021.12.12","time":"13:00"},"3":{"id":"618a916db9ba4","name":"todas","email":"todas.com","phoneNumber":"34534534","nin":"3453453453","date":"4","time":"2021"},"6":{"id":"618981f4d6701","name":"orentas","email":"email.com","phoneNumber":"12312312","nin":"12312312312","date":"2021.12.12","time":"12:30"}}